patchgan/__init__.py
patchgan/disc.py
patchgan/infer.py
patchgan/io.py
patchgan/losses.py
patchgan/train.py
patchgan/trainer.py
patchgan/transfer.py
patchgan/unet.py
patchgan/version.py
patchGAN-0.2.dist-info/LICENSE
patchGAN-0.2.dist-info/METADATA
patchGAN-0.2.dist-info/WHEEL
patchGAN-0.2.dist-info/entry_points.txt
patchGAN-0.2.dist-info/top_level.txt
patchGAN-0.2.dist-info/RECORD
