Metadata-Version: 2.1
Name: patchGAN
Version: 0.2
Summary: patchGAN image segmentation model in PyTorch
Home-page: https://github.com/ramanakumars/patchGAN
Author: Kameswara Mantha, Ramanakumar Sankar, Lucy Fortson
Author-email: manth145@umn.edu, rsankar@umn.edu, lfortson@umn.edu
License: GNU General Public License v3
License-File: LICENSE
Requires-Dist: numpy <1.25.2,>=1.21.0
Requires-Dist: torch >=1.13.0
Requires-Dist: matplotlib >3.5.0
Requires-Dist: torchvision >=0.14.0
Requires-Dist: tqdm >=4.62.3
Requires-Dist: torchinfo >=1.5.0
Requires-Dist: pyyaml
Requires-Dist: patchify
Requires-Dist: einops
